{
    "healthcare": {
        "distribution": [0.15, 0.25, 0.60],
        "source": "",
        "sample_size": 70000,
        "confidence": 0.95,
        "notes": "Healthcare shows higher positive bias, reflecting patient-provider relationships",
        "citation": ""
    },
    "finance": {
        "distribution": [0.30, 0.40, 0.30],
        "source": "",
        "sample_size": 70000,
        "confidence": 0.95,
        "notes": "More balanced distribution, skewing neutral/negative due to regulatory factors",
        "citation": ""
    },
    "technology": {
        "distribution": [0.10, 0.35, 0.55],
        "source": "",
        "sample_size": 70000,
        "confidence": 0.95,
        "notes": "Similar to e-commerce, slightly lower negative rate",
        "citation": ""
    }
} 